{
  "generator-jhipster": {
    "applicationType": "microservice",
    "authenticationType": "jwt",
    "baseName": "orderService",
    "buildTool": "maven",
    "cacheProvider": "no",
    "clientFramework": "no",
    "clientTestFrameworks": null,
    "clientTheme": null,
    "creationTimestamp": 1742884059372,
    "databaseType": "sql",
    "devDatabaseType": "mysql",
    "enableHibernateCache": null,
    "enableTranslation": true,
    "entities": ["Cart", "CartDelete"],
    "feignClient": false,
    "jhipsterVersion": "8.10.0",
    "jwtSecretKey": "MDMyYTIwZGExN2RmY2ZlY2Q0NGUzNWRhYzE5N2U1M2VjMzE4ZGE0ZTdmY2E2ZDkyN2M1MjA2NjhkMTI2M2U1YWE3ZjQ2MDFmYmQ0ZjE3Y2JjOWJjZmYwNmQzODNlNzFhN2UzNzllYTg5NmU3Y2Q4OGJkN2RlNmM5NWFhN2M0MzA=",
    "languages": ["en"],
    "lastLiquibaseTimestamp": 1744191942000,
    "microfrontend": null,
    "microfrontends": [],
    "monorepository": true,
    "nativeLanguage": "en",
    "packageName": "com.paysgift.orderservice",
    "prodDatabaseType": "mysql",
    "reactive": false,
    "searchEngine": "elasticsearch",
    "serverPort": "7004",
    "serviceDiscoveryType": "no",
    "skipClient": true,
    "skipCommitHook": true,
    "skipUserManagement": true,
    "syncUserWithIdp": null,
    "testFrameworks": [],
    "withAdminUi": null
  }
}
