{
  "annotations": {
    "changelogDate": "20250409103935"
  },
  "clientRootFolder": "paymentService",
  "databaseType": "sql",
  "dto": "mapstruct",
  "fields": [
    {
      "fieldName": "paymentTransactionId",
      "fieldType": "Long",
      "fieldValidateRules": ["required"]
    },
    {
      "fieldName": "cycle",
      "fieldType": "Integer"
    },
    {
      "fieldName": "hitDatetime",
      "fieldType": "Instant"
    },
    {
      "fieldName": "hitStatus",
      "fieldType": "Boolean"
    },
    {
      "fieldName": "createdAt",
      "fieldType": "Instant"
    },
    {
      "fieldName": "createdBy",
      "fieldType": "Long"
    },
    {
      "fieldName": "updatedAt",
      "fieldType": "Instant"
    },
    {
      "fieldName": "updatedBy",
      "fieldType": "Long"
    }
  ],
  "jpaMetamodelFiltering": false,
  "microserviceName": "paymentService",
  "name": "PaymentTransactionCampaign",
  "pagination": "pagination",
  "readOnly": true,
  "relationships": [],
  "searchEngine": "no",
  "service": "serviceImpl"
}
